ronglian_sms_sdk/SmsSDK.py
ronglian_sms_sdk/__init__.py
ronglian_sms_sdk/algorithm.py
ronglian_sms_sdk-1.0.0.dist-info/METADATA
ronglian_sms_sdk-1.0.0.dist-info/WHEEL
ronglian_sms_sdk-1.0.0.dist-info/top_level.txt
ronglian_sms_sdk-1.0.0.dist-info/RECORD
