Metadata-Version: 2.1
Name: ronglian-sms-sdk
Version: 1.0.0
Summary: RongLian SMS SDK
Home-page: https://github.com/cloopen/python-sms-sdk
Author: Panxd
Author-email: panxd@yuntongxun.com
License: UNKNOWN
Keywords: ronglian sms ronglian_sms_sdk cloopen
Platform: UNKNOWN
Classifier: Programming Language :: Python :: 3.6
Requires-Dist: requests
